pyschemer/__init__.py
pyschemer/column.py
pyschemer/relationships.py
pyschemer/schemer.py
pyschemer/table.py
pyschemer-1.1.1.dist-info/METADATA
pyschemer-1.1.1.dist-info/WHEEL
pyschemer-1.1.1.dist-info/top_level.txt
pyschemer-1.1.1.dist-info/RECORD
