Metadata-Version: 2.1
Name: pyschemer
Version: 1.1.1
Summary: A database visualization tool
Home-page: https://github.com/MitchellWeg/schemer
Author: Mitchell Weggemans
Author-email: mitchell.w@live.nl
License: BSD 2-clause
Platform: UNKNOWN
Classifier: Development Status :: 4 - Beta
Classifier: Intended Audience :: Science/Research
Classifier: License :: OSI Approved :: BSD License
Classifier: Operating System :: POSIX :: Linux
Classifier: Programming Language :: Python :: 3
Classifier: Programming Language :: Python :: 3.9
Requires-Dist: ERDot
Requires-Dist: pygraphviz
Requires-Dist: prettytable
